nonebot_plugin_homo_mathematician/__init__.py
nonebot_plugin_homo_mathematician/handle.py
nonebot_plugin_homo_mathematician/utils.py
nonebot_plugin_homo_mathematician-0.0.7.dist-info/LICENSE
nonebot_plugin_homo_mathematician-0.0.7.dist-info/METADATA
nonebot_plugin_homo_mathematician-0.0.7.dist-info/WHEEL
nonebot_plugin_homo_mathematician-0.0.7.dist-info/top_level.txt
nonebot_plugin_homo_mathematician-0.0.7.dist-info/RECORD
