Metadata-Version: 2.1
Name: nonebot-plugin-homo-mathematician
Version: 0.0.7
Summary: encapsulate logger
Home-page: https://github.com/Special-Week/Hinata-Bot/tree/main/src/plugins/homo_mathematician
Author: Special-Week
Author-email: 2749903559@qq.com
Requires-Python: >=3.8.0
License-File: LICENSE
Requires-Dist: scipy
Requires-Dist: nonebot2
Requires-Dist: nonebot-adapter-onebot
